wiflip/__init__.py
wiflip/about.py
wiflip/bibou.py
wiflip/clklabel.py
wiflip/fletcher.py
wiflip/gameset.py
wiflip/help.py
wiflip/lwin.py
wiflip/mysupervisor.py
wiflip/mytreeview.py
wiflip/mytreewidget.py
wiflip/options.py
wiflip/reprog.py
wiflip/resource_rc.py
wiflip/rscmodel.py
wiflip/servalone.py
wiflip/settings.py
wiflip/settings1.py
wiflip/setup.py
wiflip/setup_cxfreeze.py
wiflip/setupforcxfreeze.py
wiflip/supervis.py
wiflip/version.py
wiflip/wificnf.py
wiflip/wiflip.py
wiflip-0.98.29.dist-info/LICENSE
wiflip-0.98.29.dist-info/METADATA
wiflip-0.98.29.dist-info/WHEEL
wiflip-0.98.29.dist-info/entry_points.txt
wiflip-0.98.29.dist-info/top_level.txt
wiflip-0.98.29.dist-info/RECORD
