Metadata-Version: 2.2
Name: WiFlip
Version: 0.98.29
Summary: Communication tool with pps4 wifi clones
Author-email: Phil Dubious <phil.dubious@free.fr>, Garzol Garzol <garzol@free.fr>
License: Copyright (c) 2025 AA55 Consulting
Project-URL: Homepage, https://github.com/garzol/wiflip
Project-URL: Issues, https://github.com/garzol/wiflip/issues
Project-URL: Documentation, https://www.pps4.fr/wiflip
Classifier: Programming Language :: Python :: 3
Classifier: Operating System :: OS Independent
Requires-Python: >=3.6
License-File: LICENSE
Requires-Dist: PyQt5>=5.15.4
Requires-Dist: requests
Requires-Dist: bs4
Provides-Extra: gui
Requires-Dist: PyQt5; extra == "gui"
